result_type/__init__.py
result_type/async_result.py
result_type/core.py
python_result_type-1.2.1.dist-info/METADATA
python_result_type-1.2.1.dist-info/WHEEL
python_result_type-1.2.1.dist-info/licenses/LICENSE
python_result_type-1.2.1.dist-info/RECORD
