Metadata-Version: 2.4
Name: python-result-type
Version: 1.2.1
Summary: A functional programming Result type for Python with Success/Failure variants and async support
Project-URL: Homepage, https://github.com/lumduan/python-result-type
Project-URL: Documentation, https://github.com/lumduan/python-result-type#readme
Project-URL: Repository, https://github.com/lumduan/python-result-type.git
Project-URL: Issues, https://github.com/lumduan/python-result-type/issues
Author-email: batt <b@candythink.com>
License-Expression: MIT
License-File: LICENSE
Keywords: async,await,error-handling,functional-programming,monads,result-type,rust-like
Classifier: Development Status :: 5 - Production/Stable
Classifier: Intended Audience :: Developers
Classifier: License :: OSI Approved :: MIT License
Classifier: Programming Language :: Python :: 3
Classifier: Programming Language :: Python :: 3.8
Classifier: Programming Language :: Python :: 3.9
Classifier: Programming Language :: Python :: 3.10
Classifier: Programming Language :: Python :: 3.11
Classifier: Programming Language :: Python :: 3.12
Classifier: Programming Language :: Python :: 3.13
Classifier: Topic :: Software Development :: Libraries :: Python Modules
Classifier: Topic :: Utilities
Classifier: Typing :: Typed
Requires-Python: >=3.8
Provides-Extra: dev
Requires-Dist: black>=22.0.0; extra == 'dev'
Requires-Dist: mypy>=1.0.0; extra == 'dev'
Requires-Dist: pytest-asyncio>=0.21.0; extra == 'dev'
Requires-Dist: pytest-cov>=4.0.0; extra == 'dev'
Requires-Dist: pytest>=7.0.0; extra == 'dev'
Requires-Dist: ruff>=0.1.0; extra == 'dev'
